{
    "TEK.AX": {
        "short_name": "THORN TECH FPO",
        "long_name": "Thorney Technologies Ltd",
        "summary": "Thorney Technologies Ltd invests in technology related companies. The company was formerly known as Australian Renewable Fuels Limited and changed its name to Thorney Technologies Ltd in December 2016. Thorney Technologies Ltd was founded in 2005 and is based in Melbourne, Australia.",
        "currency": "AUD",
        "sector": "Basic Materials",
        "industry": "Oil & Gas Refining & Marketing",
        "exchange": "ASX",
        "market": "au_market",
        "country": "Australia",
        "state": "VIC",
        "city": "Melbourne",
        "zipcode": "3000",
        "website": "http://www.thorneytechnologies.com.au",
        "market_cap": 110668672
    }
}