{
    "AUDISK=X": {
        "short_name": "AUD/ISK",
        "currency": "ISK",
        "exchange": "CCY",
        "market": "ccy_market"
    },
    "CADISK=X": {
        "short_name": "CAD/ISK",
        "currency": "ISK",
        "exchange": "CCY",
        "market": "ccy_market"
    },
    "CHFISK=X": {
        "short_name": "CHF/ISK",
        "currency": "ISK",
        "exchange": "CCY",
        "market": "ccy_market"
    },
    "DKKISK=X": {
        "short_name": "DKK/ISK",
        "currency": "ISK",
        "exchange": "CCY",
        "market": "ccy_market"
    },
    "EURISK=X": {
        "short_name": "EUR/ISK",
        "currency": "ISK",
        "exchange": "CCY",
        "market": "ccy_market"
    },
    "GBPISK=X": {
        "short_name": "GBP/ISK",
        "currency": "ISK",
        "exchange": "CCY",
        "market": "ccy_market"
    },
    "ISK=X": {
        "short_name": "USD/ISK",
        "currency": "ISK",
        "exchange": "CCY",
        "market": "ccy_market"
    },
    "JPYISK=X": {
        "short_name": "JPY/ISK",
        "currency": "ISK",
        "exchange": "CCY",
        "market": "ccy_market"
    },
    "NOKISK=X": {
        "short_name": "NOK/ISK",
        "currency": "ISK",
        "exchange": "CCY",
        "market": "ccy_market"
    },
    "SEKISK=X": {
        "short_name": "SEK/ISK",
        "currency": "ISK",
        "exchange": "CCY",
        "market": "ccy_market"
    }
}