{
    "002716.SZ": {
        "short_name": "CHENZHOU CITY JING",
        "long_name": "Chenzhou City Jingui Silver Industry Co., Ltd.",
        "summary": "Chenzhou City Jingui Silver Industry Co., Ltd. engages in the research and development, production, smelting, processing, and export of silver in China. It primarily offers high-purity silver and silver products, high-purity silver nitrates, electrolytic leads, crude leads, etc. The company was founded in 2004 and is headquartered in Chenzhou, China.",
        "currency": "CNY",
        "sector": "Basic Materials",
        "industry": "Silver",
        "exchange": "SHZ",
        "market": "cn_market",
        "country": "China",
        "city": "Chenzhou"
    }
}