{
    "FCT-AUD": {
        "short_name": "Factom AUD",
        "cryptocurrency": "FCT",
        "currency": "AUD",
        "summary": "Factom (FCT) is a cryptocurrency . Factom has a current supply of 9,771,445.62139246. The last known price of Factom is 2.3486145 USD and is down -4.44 over the last 24 hours. It is currently trading on 3 active market(s) with $37,085.91 traded over the last 24 hours. More information can be found at https://www.factomprotocol.org.",
        "exchange": "CCC",
        "market": "ccc_market"
    },
    "FCT-BTC": {
        "short_name": "Factom BTC",
        "cryptocurrency": "FCT",
        "currency": "BTC",
        "summary": "Factom (FCT) is a cryptocurrency . Factom has a current supply of 9,771,445.62139246. The last known price of Factom is 2.3486145 USD and is down -4.44 over the last 24 hours. It is currently trading on 3 active market(s) with $37,085.91 traded over the last 24 hours. More information can be found at https://www.factomprotocol.org.",
        "exchange": "CCC",
        "market": "ccc_market"
    },
    "FCT-CAD": {
        "short_name": "Factom CAD",
        "cryptocurrency": "FCT",
        "currency": "CAD",
        "summary": "Factom (FCT) is a cryptocurrency . Factom has a current supply of 9,771,445.62139246. The last known price of Factom is 2.3486145 USD and is down -4.44 over the last 24 hours. It is currently trading on 3 active market(s) with $37,085.91 traded over the last 24 hours. More information can be found at https://www.factomprotocol.org.",
        "exchange": "CCC",
        "market": "ccc_market"
    },
    "FCT-CNY": {
        "short_name": "Factom CNY",
        "cryptocurrency": "FCT",
        "currency": "CNY",
        "summary": "Factom (FCT) is a cryptocurrency . Factom has a current supply of 9,771,445.62139246. The last known price of Factom is 2.3486145 USD and is down -4.44 over the last 24 hours. It is currently trading on 3 active market(s) with $37,085.91 traded over the last 24 hours. More information can be found at https://www.factomprotocol.org.",
        "exchange": "CCC",
        "market": "ccc_market"
    },
    "FCT-ETH": {
        "short_name": "Factom ETH",
        "cryptocurrency": "FCT",
        "currency": "ETH",
        "summary": "Factom (FCT) is a cryptocurrency . Factom has a current supply of 9,771,445.62139246. The last known price of Factom is 2.3486145 USD and is down -4.44 over the last 24 hours. It is currently trading on 3 active market(s) with $37,085.91 traded over the last 24 hours. More information can be found at https://www.factomprotocol.org.",
        "exchange": "CCC",
        "market": "ccc_market"
    },
    "FCT-EUR": {
        "short_name": "Factom EUR",
        "cryptocurrency": "FCT",
        "currency": "EUR",
        "summary": "Factom (FCT) is a cryptocurrency . Factom has a current supply of 9,771,445.62139246. The last known price of Factom is 2.3486145 USD and is down -4.44 over the last 24 hours. It is currently trading on 3 active market(s) with $37,085.91 traded over the last 24 hours. More information can be found at https://www.factomprotocol.org.",
        "exchange": "CCC",
        "market": "ccc_market"
    },
    "FCT-GBP": {
        "short_name": "Factom GBP",
        "cryptocurrency": "FCT",
        "currency": "GBP",
        "summary": "Factom (FCT) is a cryptocurrency . Factom has a current supply of 9,771,445.62139246. The last known price of Factom is 2.3486145 USD and is down -4.44 over the last 24 hours. It is currently trading on 3 active market(s) with $37,085.91 traded over the last 24 hours. More information can be found at https://www.factomprotocol.org.",
        "exchange": "CCC",
        "market": "ccc_market"
    },
    "FCT-JPY": {
        "short_name": "Factom JPY",
        "cryptocurrency": "FCT",
        "currency": "JPY",
        "summary": "Factom (FCT) is a cryptocurrency . Factom has a current supply of 9,771,445.62139246. The last known price of Factom is 2.3486145 USD and is down -4.44 over the last 24 hours. It is currently trading on 3 active market(s) with $37,085.91 traded over the last 24 hours. More information can be found at https://www.factomprotocol.org.",
        "exchange": "CCC",
        "market": "ccc_market"
    },
    "FCT-KRW": {
        "short_name": "Factom KRW",
        "cryptocurrency": "FCT",
        "currency": "KRW",
        "summary": "Factom (FCT) is a cryptocurrency . Factom has a current supply of 9,771,445.62139246. The last known price of Factom is 2.3486145 USD and is down -4.44 over the last 24 hours. It is currently trading on 3 active market(s) with $37,085.91 traded over the last 24 hours. More information can be found at https://www.factomprotocol.org.",
        "exchange": "CCC",
        "market": "ccc_market"
    },
    "FCT-USD": {
        "short_name": "Factom USD",
        "cryptocurrency": "FCT",
        "currency": "USD",
        "summary": "Factom (FCT) is a cryptocurrency . Factom has a current supply of 9,771,445.62139246. The last known price of Factom is 2.3486145 USD and is down -4.44 over the last 24 hours. It is currently trading on 3 active market(s) with $37,085.91 traded over the last 24 hours. More information can be found at https://www.factomprotocol.org.",
        "exchange": "CCC",
        "market": "ccc_market"
    }
}