{
    "GRC-AUD": {
        "short_name": "GridCoin AUD",
        "cryptocurrency": "GRC",
        "currency": "AUD",
        "summary": "GridCoin (GRC) is a cryptocurrency . Users are able to generate GRC through the process of mining. GridCoin has a current supply of 442,177,616.9306 with 411,524,584.7824196 in circulation. The last known price of GridCoin is 0.00666841 USD and is down -1.65 over the last 24 hours. It is currently trading on 5 active market(s) with $881.06 traded over the last 24 hours. More information can be found at http://www.gridcoin.us/.",
        "exchange": "CCC",
        "market": "ccc_market"
    },
    "GRC-BTC": {
        "short_name": "GridCoin BTC",
        "cryptocurrency": "GRC",
        "currency": "BTC",
        "summary": "GridCoin (GRC) is a cryptocurrency . Users are able to generate GRC through the process of mining. GridCoin has a current supply of 442,177,616.9306 with 411,524,584.7824196 in circulation. The last known price of GridCoin is 0.00666841 USD and is down -1.65 over the last 24 hours. It is currently trading on 5 active market(s) with $881.06 traded over the last 24 hours. More information can be found at http://www.gridcoin.us/.",
        "exchange": "CCC",
        "market": "ccc_market"
    },
    "GRC-CAD": {
        "short_name": "GridCoin CAD",
        "cryptocurrency": "GRC",
        "currency": "CAD",
        "summary": "GridCoin (GRC) is a cryptocurrency . Users are able to generate GRC through the process of mining. GridCoin has a current supply of 442,177,616.9306 with 411,524,584.7824196 in circulation. The last known price of GridCoin is 0.00666841 USD and is down -1.65 over the last 24 hours. It is currently trading on 5 active market(s) with $881.06 traded over the last 24 hours. More information can be found at http://www.gridcoin.us/.",
        "exchange": "CCC",
        "market": "ccc_market"
    },
    "GRC-CNY": {
        "short_name": "GridCoin CNY",
        "cryptocurrency": "GRC",
        "currency": "CNY",
        "summary": "GridCoin (GRC) is a cryptocurrency . Users are able to generate GRC through the process of mining. GridCoin has a current supply of 442,177,616.9306 with 411,524,584.7824196 in circulation. The last known price of GridCoin is 0.00666841 USD and is down -1.65 over the last 24 hours. It is currently trading on 5 active market(s) with $881.06 traded over the last 24 hours. More information can be found at http://www.gridcoin.us/.",
        "exchange": "CCC",
        "market": "ccc_market"
    },
    "GRC-ETH": {
        "short_name": "GridCoin ETH",
        "cryptocurrency": "GRC",
        "currency": "ETH",
        "summary": "GridCoin (GRC) is a cryptocurrency . Users are able to generate GRC through the process of mining. GridCoin has a current supply of 442,177,616.9306 with 411,524,584.7824196 in circulation. The last known price of GridCoin is 0.00666841 USD and is down -1.65 over the last 24 hours. It is currently trading on 5 active market(s) with $881.06 traded over the last 24 hours. More information can be found at http://www.gridcoin.us/.",
        "exchange": "CCC",
        "market": "ccc_market"
    },
    "GRC-EUR": {
        "short_name": "GridCoin EUR",
        "cryptocurrency": "GRC",
        "currency": "EUR",
        "summary": "GridCoin (GRC) is a cryptocurrency . Users are able to generate GRC through the process of mining. GridCoin has a current supply of 442,177,616.9306 with 411,524,584.7824196 in circulation. The last known price of GridCoin is 0.00666841 USD and is down -1.65 over the last 24 hours. It is currently trading on 5 active market(s) with $881.06 traded over the last 24 hours. More information can be found at http://www.gridcoin.us/.",
        "exchange": "CCC",
        "market": "ccc_market"
    },
    "GRC-GBP": {
        "short_name": "GridCoin GBP",
        "cryptocurrency": "GRC",
        "currency": "GBP",
        "summary": "GridCoin (GRC) is a cryptocurrency . Users are able to generate GRC through the process of mining. GridCoin has a current supply of 442,177,616.9306 with 411,524,584.7824196 in circulation. The last known price of GridCoin is 0.00666841 USD and is down -1.65 over the last 24 hours. It is currently trading on 5 active market(s) with $881.06 traded over the last 24 hours. More information can be found at http://www.gridcoin.us/.",
        "exchange": "CCC",
        "market": "ccc_market"
    },
    "GRC-INR": {
        "short_name": "GridCoin INR",
        "cryptocurrency": "GRC",
        "currency": "INR",
        "summary": "GridCoin (GRC) is a cryptocurrency . Users are able to generate GRC through the process of mining. GridCoin has a current supply of 442,177,616.9306 with 411,524,584.7824196 in circulation. The last known price of GridCoin is 0.00666841 USD and is down -1.65 over the last 24 hours. It is currently trading on 5 active market(s) with $881.06 traded over the last 24 hours. More information can be found at http://www.gridcoin.us/.",
        "exchange": "CCC",
        "market": "ccc_market"
    },
    "GRC-JPY": {
        "short_name": "GridCoin JPY",
        "cryptocurrency": "GRC",
        "currency": "JPY",
        "summary": "GridCoin (GRC) is a cryptocurrency . Users are able to generate GRC through the process of mining. GridCoin has a current supply of 442,177,616.9306 with 411,524,584.7824196 in circulation. The last known price of GridCoin is 0.00666841 USD and is down -1.65 over the last 24 hours. It is currently trading on 5 active market(s) with $881.06 traded over the last 24 hours. More information can be found at http://www.gridcoin.us/.",
        "exchange": "CCC",
        "market": "ccc_market"
    },
    "GRC-KRW": {
        "short_name": "GridCoin KRW",
        "cryptocurrency": "GRC",
        "currency": "KRW",
        "summary": "GridCoin (GRC) is a cryptocurrency . Users are able to generate GRC through the process of mining. GridCoin has a current supply of 442,177,616.9306 with 411,524,584.7824196 in circulation. The last known price of GridCoin is 0.00666841 USD and is down -1.65 over the last 24 hours. It is currently trading on 5 active market(s) with $881.06 traded over the last 24 hours. More information can be found at http://www.gridcoin.us/.",
        "exchange": "CCC",
        "market": "ccc_market"
    },
    "GRC-RUB": {
        "short_name": "GridCoin RUB",
        "cryptocurrency": "GRC",
        "currency": "RUB",
        "summary": "GridCoin (GRC) is a cryptocurrency . Users are able to generate GRC through the process of mining. GridCoin has a current supply of 442,177,616.9306 with 411,524,584.7824196 in circulation. The last known price of GridCoin is 0.00666841 USD and is down -1.65 over the last 24 hours. It is currently trading on 5 active market(s) with $881.06 traded over the last 24 hours. More information can be found at http://www.gridcoin.us/.",
        "exchange": "CCC",
        "market": "ccc_market"
    },
    "GRC-USD": {
        "short_name": "GridCoin USD",
        "cryptocurrency": "GRC",
        "currency": "USD",
        "summary": "GridCoin (GRC) is a cryptocurrency . Users are able to generate GRC through the process of mining. GridCoin has a current supply of 442,177,616.9306 with 411,524,584.7824196 in circulation. The last known price of GridCoin is 0.00666841 USD and is down -1.65 over the last 24 hours. It is currently trading on 5 active market(s) with $881.06 traded over the last 24 hours. More information can be found at http://www.gridcoin.us/.",
        "exchange": "CCC",
        "market": "ccc_market"
    }
}