{"SCC2-EUR": {"short_name": "StakeCubeCoin EUR", "cryptocurrency": "SCC2", "currency": "EUR", "summary": "StakeCubeCoin (SCC) is a cryptocurrency . Users are able to generate SCC through the process of mining. StakeCubeCoin has a current supply of 9,352,167.75187097 with 8,053,167.75187097 in circulation. The last known price of StakeCubeCoin is 0.62416508 USD and is down -6.20 over the last 24 hours. It is currently trading on 19 active market(s) with $10,442.19 traded over the last 24 hours. More information can be found at https://stakecube.net.", "exchange": "CCC", "market": "ccc_market"}, "SCC2-GBP": {"short_name": "StakeCubeCoin GBP", "cryptocurrency": "SCC2", "currency": "GBP", "summary": "StakeCubeCoin (SCC) is a cryptocurrency . Users are able to generate SCC through the process of mining. StakeCubeCoin has a current supply of 9,352,167.75187097 with 8,053,167.75187097 in circulation. The last known price of StakeCubeCoin is 0.62416508 USD and is down -6.20 over the last 24 hours. It is currently trading on 19 active market(s) with $10,442.19 traded over the last 24 hours. More information can be found at https://stakecube.net.", "exchange": "CCC", "market": "ccc_market"}}