{
    "TT-AUD": {
        "short_name": "ThunderToken AUD",
        "cryptocurrency": "TT",
        "currency": "AUD",
        "summary": "Thunder Token (TT) is a cryptocurrency . Thunder Token has a current supply of 10,000,000,000 with 5,887,903,652.667712 in circulation. The last known price of Thunder Token is 0.00488665 USD and is down -4.75 over the last 24 hours. It is currently trading on 13 active market(s) with $4,381,464.37 traded over the last 24 hours. More information can be found at https://www.thundercore.com.",
        "exchange": "CCC",
        "market": "ccc_market"
    },
    "TT-BTC": {
        "short_name": "ThunderToken BTC",
        "cryptocurrency": "TT",
        "currency": "BTC",
        "summary": "Thunder Token (TT) is a cryptocurrency . Thunder Token has a current supply of 10,000,000,000 with 5,887,903,652.667712 in circulation. The last known price of Thunder Token is 0.00488665 USD and is down -4.75 over the last 24 hours. It is currently trading on 13 active market(s) with $4,381,464.37 traded over the last 24 hours. More information can be found at https://www.thundercore.com.",
        "exchange": "CCC",
        "market": "ccc_market"
    },
    "TT-CAD": {
        "short_name": "ThunderToken CAD",
        "cryptocurrency": "TT",
        "currency": "CAD",
        "summary": "Thunder Token (TT) is a cryptocurrency . Thunder Token has a current supply of 10,000,000,000 with 5,887,903,652.667712 in circulation. The last known price of Thunder Token is 0.00488665 USD and is down -4.75 over the last 24 hours. It is currently trading on 13 active market(s) with $4,381,464.37 traded over the last 24 hours. More information can be found at https://www.thundercore.com.",
        "exchange": "CCC",
        "market": "ccc_market"
    },
    "TT-CNY": {
        "short_name": "ThunderToken CNY",
        "cryptocurrency": "TT",
        "currency": "CNY",
        "summary": "Thunder Token (TT) is a cryptocurrency . Thunder Token has a current supply of 10,000,000,000 with 5,887,903,652.667712 in circulation. The last known price of Thunder Token is 0.00488665 USD and is down -4.75 over the last 24 hours. It is currently trading on 13 active market(s) with $4,381,464.37 traded over the last 24 hours. More information can be found at https://www.thundercore.com.",
        "exchange": "CCC",
        "market": "ccc_market"
    },
    "TT-ETH": {
        "short_name": "ThunderToken ETH",
        "cryptocurrency": "TT",
        "currency": "ETH",
        "summary": "Thunder Token (TT) is a cryptocurrency . Thunder Token has a current supply of 10,000,000,000 with 5,887,903,652.667712 in circulation. The last known price of Thunder Token is 0.00488665 USD and is down -4.75 over the last 24 hours. It is currently trading on 13 active market(s) with $4,381,464.37 traded over the last 24 hours. More information can be found at https://www.thundercore.com.",
        "exchange": "CCC",
        "market": "ccc_market"
    },
    "TT-EUR": {
        "short_name": "ThunderToken EUR",
        "cryptocurrency": "TT",
        "currency": "EUR",
        "summary": "Thunder Token (TT) is a cryptocurrency . Thunder Token has a current supply of 10,000,000,000 with 5,887,903,652.667712 in circulation. The last known price of Thunder Token is 0.00488665 USD and is down -4.75 over the last 24 hours. It is currently trading on 13 active market(s) with $4,381,464.37 traded over the last 24 hours. More information can be found at https://www.thundercore.com.",
        "exchange": "CCC",
        "market": "ccc_market"
    },
    "TT-GBP": {
        "short_name": "ThunderToken GBP",
        "cryptocurrency": "TT",
        "currency": "GBP",
        "summary": "Thunder Token (TT) is a cryptocurrency . Thunder Token has a current supply of 10,000,000,000 with 5,887,903,652.667712 in circulation. The last known price of Thunder Token is 0.00488665 USD and is down -4.75 over the last 24 hours. It is currently trading on 13 active market(s) with $4,381,464.37 traded over the last 24 hours. More information can be found at https://www.thundercore.com.",
        "exchange": "CCC",
        "market": "ccc_market"
    },
    "TT-INR": {
        "short_name": "ThunderToken INR",
        "cryptocurrency": "TT",
        "currency": "INR",
        "summary": "Thunder Token (TT) is a cryptocurrency . Thunder Token has a current supply of 10,000,000,000 with 5,887,903,652.667712 in circulation. The last known price of Thunder Token is 0.00488665 USD and is down -4.75 over the last 24 hours. It is currently trading on 13 active market(s) with $4,381,464.37 traded over the last 24 hours. More information can be found at https://www.thundercore.com.",
        "exchange": "CCC",
        "market": "ccc_market"
    },
    "TT-JPY": {
        "short_name": "ThunderToken JPY",
        "cryptocurrency": "TT",
        "currency": "JPY",
        "summary": "Thunder Token (TT) is a cryptocurrency . Thunder Token has a current supply of 10,000,000,000 with 5,887,903,652.667712 in circulation. The last known price of Thunder Token is 0.00488665 USD and is down -4.75 over the last 24 hours. It is currently trading on 13 active market(s) with $4,381,464.37 traded over the last 24 hours. More information can be found at https://www.thundercore.com.",
        "exchange": "CCC",
        "market": "ccc_market"
    },
    "TT-KRW": {
        "short_name": "ThunderToken KRW",
        "cryptocurrency": "TT",
        "currency": "KRW",
        "summary": "Thunder Token (TT) is a cryptocurrency . Thunder Token has a current supply of 10,000,000,000 with 5,887,903,652.667712 in circulation. The last known price of Thunder Token is 0.00488665 USD and is down -4.75 over the last 24 hours. It is currently trading on 13 active market(s) with $4,381,464.37 traded over the last 24 hours. More information can be found at https://www.thundercore.com.",
        "exchange": "CCC",
        "market": "ccc_market"
    },
    "TT-RUB": {
        "short_name": "ThunderToken RUB",
        "cryptocurrency": "TT",
        "currency": "RUB",
        "summary": "Thunder Token (TT) is a cryptocurrency . Thunder Token has a current supply of 10,000,000,000 with 5,887,903,652.667712 in circulation. The last known price of Thunder Token is 0.00488665 USD and is down -4.75 over the last 24 hours. It is currently trading on 13 active market(s) with $4,381,464.37 traded over the last 24 hours. More information can be found at https://www.thundercore.com.",
        "exchange": "CCC",
        "market": "ccc_market"
    },
    "TT-USD": {
        "short_name": "ThunderToken USD",
        "cryptocurrency": "TT",
        "currency": "USD",
        "summary": "Thunder Token (TT) is a cryptocurrency . Thunder Token has a current supply of 10,000,000,000 with 5,887,903,652.667712 in circulation. The last known price of Thunder Token is 0.00488665 USD and is down -4.75 over the last 24 hours. It is currently trading on 13 active market(s) with $4,381,464.37 traded over the last 24 hours. More information can be found at https://www.thundercore.com.",
        "exchange": "CCC",
        "market": "ccc_market"
    }
}