{
  "MEGACPO.MX": {
    "city": "Guadalajara",
    "country": "Mexico",
    "currency": "MXN",
    "exchange": "MEX",
    "industry": "Entertainment",
    "long_name": "Megacable Holdings, S. A. B. de C. V.",
    "market": "mx_market",
    "market_cap": "Mid Cap",
    "sector": "Communication Services",
    "short_name": "MEGACABLE HOLDINGS SAB DE CV",
    "state": "JA",
    "summary": "Megacable Holdings, S. A. B. de C. V. engages in the installation, operation, maintenance, and exploitation of telephone, Internet, and television cable signal distribution systems. It operates through Cable, Internet, Telephony, Business, and Other segments. The company operates cable television systems in various states of Mexico; and offers high-speed Internet services to residential and commercial customers, as well as fixed digital telephony services to residential and commercial customers. It also produces and broadcasts TV programs, as well as offers distribution services from various points and channels, virtual private network, and other network services. The company provides video services to 3,224,798 subscribers; Internet services to 3,097,628 subscribers; and telephony services to 2,130,538 subscribers. It is also involved in the leasing of equipment and infrastructure for providing cable, Internet, and telephone services; provision of technical, sales, and administrative personnel services; and operation of Video rola' channel. Megacable Holdings, S. A. B. de C. V. is headquartered in Guadalajara, Mexico.",
    "website": "http://www.megacable.com.mx",
    "zipcode": "44900"
  },
  "MHSDF": {
    "city": "Guadalajara",
    "country": "Mexico",
    "currency": "USD",
    "exchange": "PNK",
    "industry": "Entertainment",
    "long_name": "Megacable Holdings, S. A. B. de C. V.",
    "market": "us_market",
    "market_cap": "Mid Cap",
    "sector": "Communication Services",
    "short_name": "MEGACABLE HOLDINGS SAB DE CV",
    "state": "JA",
    "summary": "Megacable Holdings, S. A. B. de C. V. engages in the installation, operation, maintenance, and exploitation of telephone, Internet, and television cable signal distribution systems. It operates through Cable, Internet, Telephony, Business, and Other segments. The company operates cable television systems in various states of Mexico; and offers high-speed Internet services to residential and commercial customers, as well as fixed digital telephony services to residential and commercial customers. It also produces and broadcasts TV programs, as well as offers distribution services from various points and channels, virtual private network, and other network services. The company provides video services to 3,224,798 subscribers; Internet services to 3,097,628 subscribers; and telephony services to 2,130,538 subscribers. It is also involved in the leasing of equipment and infrastructure for providing cable, Internet, and telephone services; provision of technical, sales, and administrative personnel services; and operation of Video rola' channel. Megacable Holdings, S. A. B. de C. V. is headquartered in Guadalajara, Mexico.",
    "website": "http://www.megacable.com.mx",
    "zipcode": "44900"
  }
}
