{
    "ISS.CO": {
        "short_name": "ISS A/S",
        "long_name": "ISS A/S",
        "summary": "ISS A/S provides workplace management and facility services. It offers office, hospital, laboratory, food hygiene, hospitality and events cleaning services; and hospitality, catering, fine dining and event catering, and micro-kitchens and vending services, as well as operates restaurants, pop-up or high street concept stores, coffee bars, and power plants. The company also provides security services comprising security awareness training, surveillance, workplace safety and emergency management, consulting, security risk management, and technical installation services. In addition, it offers support services, which include front desk and reception, meeting and conference management, switchboards and service desk, concierge, mail and courier, document, executive and administrative support, and experience curation and management services. Further, the company provides energy management, asset management, capital projects, building structure and fabric, critical environments, property maintenance, and waste management services. Additionally, it designs and delivers workplace strategies and solutions, such as portfolio strategy, curated experience and workplace strategy, workplace design, service design, relocation strategy, capital projects, mental rebuild, and co-working services. ISS A/S was founded in 1901 and is headquartered in S\u00c3\u00b8borg, Denmark.",
        "currency": "DKK",
        "sector": "Industrials",
        "industry": "Specialty Business Services",
        "exchange": "CPH",
        "market": "dk_market",
        "country": "Denmark",
        "state": null,
        "city": "S\u00c3\u00b8borg",
        "zipcode": "2860",
        "website": "http://www.issworld.com",
        "full_time_employees": 284210
    },
    "ISSDY": {
        "short_name": "ISS A/S",
        "long_name": "ISS A/S",
        "summary": "ISS A/S provides workplace management and facility services. It offers office, hospital, laboratory, food hygiene, hospitality and events cleaning services; and hospitality, catering, fine dining and event catering, and micro-kitchens and vending services, as well as operates restaurants, pop-up or high street concept stores, coffee bars, and power plants. The company also provides security services comprising security awareness training, surveillance, workplace safety and emergency management, consulting, security risk management, and technical installation services. In addition, it offers support services, which include front desk and reception, meeting and conference management, switchboards and service desk, concierge, mail and courier, document, executive and administrative support, and experience curation and management services. Further, the company provides energy management, asset management, capital projects, building structure and fabric, critical environments, property maintenance, and waste management services. Additionally, it designs and delivers workplace strategies and solutions, such as portfolio strategy, curated experience and workplace strategy, workplace design, service design, relocation strategy, capital projects, mental rebuild, and co-working services. ISS A/S was founded in 1901 and is headquartered in S\u00c3\u00b8borg, Denmark.",
        "currency": "USD",
        "sector": "Industrials",
        "industry": "Specialty Business Services",
        "exchange": "PNK",
        "market": "us_market",
        "country": "Denmark",
        "state": null,
        "city": "S\u00c3\u00b8borg",
        "zipcode": "2860",
        "website": "http://www.issworld.com",
        "full_time_employees": 284210
    }
}