{
    "0P0000TY7D.F": {
        "short_name": "SEB Life International Dexia Bo",
        "long_name": "SEB Life International Dexia Bonds Euro Long Term EUR",
        "currency": "EUR",
        "summary": "The fund invests principally in euro denominated bonds and related securities at fixed or variable rates, indexed, subordinated or backed by assets with a duration (i.e. a sensitivity to interest rate) of at least 6 years. The selected bonds are issued by governments, public & semi-public sector entities, and private companies, with a minimum rating of BBB-/Baa3 by one of the 3 main ratings agencies at the time of their acquisition. The fund carries out an active currency hedging policy versus the euro, and may use derivatives for efficient portfolio management purposes (hedge, exposure, arbitrage).",
        "manager_name": "Regis  Lanove",
        "manager_bio": "",
        "category": "EUR Bond - Long Term",
        "family": "SEB Life International",
        "exchange": "FRA",
        "market": "dr_market",
        "total_assets": 93
    }
}