{
    "5EG.SI": {
        "short_name": "$ Zhongxin Fruit",
        "long_name": "Zhongxin Fruit and Juice Limited",
        "summary": "Zhongxin Fruit and Juice Limited, an investment holding company, produces and sells fruit and vegetable juice concentrates and beverages in the People's Republic of China. It primarily offers concentrated apple juice for exports to multinational F&B corporations in the United States, the European Union, South Africa, Canada, Japan, and Australia. The company was formerly known as New Lakeside Holdings Limited and changed its name to Zhongxin Fruit and Juice Limited in February 2013. The company was incorporated in 2002 and is based in Singapore. Zhongxin Fruit and Juice Limited is a subsidiary of SDIC Zhonglu Fruit Juice Co., Ltd.",
        "currency": "SGD",
        "sector": "Consumer Defensive",
        "industry": "Beverages - Non-Alcoholic",
        "exchange": "SES",
        "market": "sg_market",
        "country": "Singapore",
        "state": null,
        "city": "Singapore",
        "zipcode": "609916",
        "website": "http://zhongxinfj.com",
        "market_cap": "Nano Cap"
    },
    "F03.SI": {
        "short_name": "Food Empire",
        "long_name": "Food Empire Holdings Limited",
        "summary": "Food Empire Holdings Limited, an investment holding company, operates as a branding and manufacturing company specializing in the food and beverage industry. Its products include instant beverage products, frozen convenience food, confectionery, and snacks. The company offers beverage products comprising regular and flavored coffee mixes and cappuccinos, chocolate drinks, and flavored fruit teas, as well as markets instant breakfast cereal, frozen foods, and snack items; and raw ingredients to other food manufacturers under its B2B arm. In addition, it engages in the distribution, procurement, wholesale, and trade of beverage products; general trading activities; import, export, and distribution of food products; procurement and sale of raw materials, processed and non-processed food, and finished goods; management and finance support activities; ownership and leasing of factory space and equipment; sale of rights to use intellectual property against royalty rights; advertising; office administrative activities; and operation of cafes and restaurants. The company offers its products under the MacCoffee, Petrovskaya Sloboda, Caf\u00c3\u00a9 PHO, Klassno, CafeRite, NutriRite, Hillway, Hyson, OrienBites, and Kracks brands. The company sells its products to approximately 50 countries, including Russia, Ukraine, Kazakhstan, Central Asia, China, Indochina, the Middle East, Africa, Mongolia, Europe, and the United States. Food Empire Holdings Limited was founded in 1992 and is based in Singapore.",
        "currency": "SGD",
        "sector": "Consumer Defensive",
        "industry": "Beverages - Non-Alcoholic",
        "exchange": "SES",
        "market": "sg_market",
        "country": "Singapore",
        "state": null,
        "city": "Singapore",
        "zipcode": "369649",
        "website": "http://www.foodempire.com",
        "market_cap": "Small Cap"
    }
}