{
  "FCFE18.MX": {
    "city": "Mexico City",
    "country": "Mexico",
    "currency": "MXN",
    "exchange": "MEX",
    "industry": "REIT - Specialty",
    "long_name": "CFECAPITAL, S. De R.L. De C.V.",
    "market": "mx_market",
    "market_cap": null,
    "sector": "Real Estate",
    "short_name": "CIBANCO SA INSTIT DE BANCA MULT",
    "state": null,
    "summary": "CFECAPITAL, S. De R.L. De C.V. operates as a trust for investment in energy and infrastructure in Mexico. It focuses on acquiring and owning electric power transmission, generation, and distribution assets. The company was incorporated in 2017 and is based in Mexico City, Mexico.",
    "website": "http://cfecapital.com.mx",
    "zipcode": "11000"
  }
}
