{
    "PRO.MC": {
        "short_name": "PROEDUCA ALTUS, S.A.",
        "long_name": "Proeduca Altus, S.A.",
        "summary": "Proeduca Altus, S.A. provides online education services. The company provides its students with a platform designed primarily for management of online learning with resources, such as virtual classrooms, forums, and collaborative work spaces, as well as digital library and virtual museums. Its platform allows its students to contact directly with other classmates, teachers, and tutors from whom they receive educational support and personalized attention. The company serves students in approximately 90 countries primarily in Spain, Ecuador, Colombia, Mexico, Peru, Argentina, Bolivia, and the United States. Proeduca Altus, S.A. is based in Madrid, Spain.",
        "currency": "EUR",
        "sector": "Consumer Defensive",
        "industry": "Education & Training Services",
        "exchange": "MCE",
        "market": "es_market",
        "country": "Spain",
        "state": null,
        "city": "Madrid",
        "zipcode": "28040",
        "website": "http://www.grupoproeduca.com",
        "market_cap": "Small Cap"
    }
}