{"29O.F": {"short_name": "CARRARO S.P.A.  EO 0,52", "long_name": "Carraro S.p.A.", "summary": "Carraro S.p.A. manufactures and sells power transmission systems for tractors and off-highway vehicles in Italy, other European countries, North and South America, Asia, and other non-European countries. The company gears, axles, and transmissions systems for agricultural, construction, and automotive equipment; tractors; transmission/engine systems for the material handling industry; and high-precision gears and drive shafts for industrial plants, escalators, robotics, and wind turbines, as well as for the railway industry. It also provides engineering and after sales services; and original spare parts. The company was founded in 1932 and is headquartered in Campodarsego, Italy. Carraro S.p.A. is a subsidiary of Finaid S.p.A.", "currency": "EUR", "sector": "Industrials", "industry": "Farm & Heavy Construction Machinery", "exchange": "FRA", "market": "dr_market", "country": "Italy", "city": "Campodarsego"}, "CARR.MI": {"short_name": "CARRARO", "long_name": "Carraro S.p.A.", "summary": "Carraro S.p.A. manufactures and sells power transmission systems for tractors and off-highway vehicles in Italy, other European countries, North and South America, Asia, and other non-European countries. The company gears, axles, and transmissions systems for agricultural, construction, and automotive equipment; tractors; transmission/engine systems for the material handling industry; and high-precision gears and drive shafts for industrial plants, escalators, robotics, and wind turbines, as well as for the railway industry. It also provides engineering and after sales services; and original spare parts. The company was founded in 1932 and is headquartered in Campodarsego, Italy. Carraro S.p.A. is a subsidiary of Finaid S.p.A.", "currency": "EUR", "sector": "Industrials", "industry": "Farm & Heavy Construction Machinery", "exchange": "MIL", "market": "it_market", "country": "Italy", "city": "Campodarsego"}}